tests/__init__.py
tests/conftest.py
tests/api/__init__.py
tests/api/test_bot.py
tests/api/chats/__init__.py
tests/api/chats/test_chat.py
tests/api/chats/test_chats.py
tests/api/chats/test_friend.py
tests/api/chats/test_group.py
tests/api/chats/test_groups.py
tests/api/chats/test_member.py
tests/api/chats/test_mp.py
tests/api/chats/test_user.py
tests/api/messages/__init__.py
tests/api/messages/test_message.py
tests/ext/__init__.py
tests/utils/__init__.py
wxpy/__compat__.py
wxpy/__init__.py
wxpy/__main__.py
wxpy/exceptions.py
wxpy/api/__init__.py
wxpy/api/bot.py
wxpy/api/consts.py
wxpy/api/core.py
wxpy/api/data.py
wxpy/api/uris.py
wxpy/api/chats/__init__.py
wxpy/api/chats/chat.py
wxpy/api/chats/chats.py
wxpy/api/chats/friend.py
wxpy/api/chats/group.py
wxpy/api/chats/member.py
wxpy/api/chats/mp.py
wxpy/api/chats/user.py
wxpy/api/messages/__init__.py
wxpy/api/messages/message.py
wxpy/api/messages/message_config.py
wxpy/api/messages/message_types.py
wxpy/api/messages/messages.py
wxpy/api/messages/registered.py
wxpy/api/messages/sent_message.py
wxpy/compatible/__init__.py
wxpy/compatible/utils.py
wxpy/ext/__init__.py
wxpy/ext/logging_with_wechat.py
wxpy/ext/sync_message_in_groups.py
wxpy/ext/talk_bot_utils.py
wxpy/ext/tuling.py
wxpy/ext/xiaoi.py
wxpy/utils/__init__.py
wxpy/utils/console.py
wxpy/utils/misc.py
wxpy/utils/puid_map.py
wxpy/utils/tools.py
bl_wxpy-0.6.13.dist-info/LICENSE
bl_wxpy-0.6.13.dist-info/METADATA
bl_wxpy-0.6.13.dist-info/WHEEL
bl_wxpy-0.6.13.dist-info/entry_points.txt
bl_wxpy-0.6.13.dist-info/top_level.txt
bl_wxpy-0.6.13.dist-info/RECORD
