Metadata-Version: 2.1
Name: bl-wxpy
Version: 0.6.13
Summary: wxpy 定制版, 基于 https://github.com/youfou/wxpy:new-core 分支(不使用 itChat)
Home-page: https://github.com/frkhit/bl-wxpy
Author: frkhit
Author-email: frkhit@gmail.com
License: MIT
Keywords: 微信,WeChat,API
Platform: UNKNOWN
Classifier: Development Status :: 4 - Beta
Classifier: License :: OSI Approved :: MIT License
Classifier: Programming Language :: Python
Classifier: Programming Language :: Python :: 2.7
Classifier: Programming Language :: Python :: 3.4
Classifier: Programming Language :: Python :: 3.5
Classifier: Programming Language :: Python :: 3.6
Classifier: Operating System :: OS Independent
Classifier: Topic :: Communications :: Chat
Classifier: Topic :: Utilities
Requires-Dist: requests (>=2.4.0)
Requires-Dist: pyqrcode
Requires-Dist: pypng
Requires-Dist: future
